dash_flow_diagrams/Background.py
dash_flow_diagrams/Controls.py
dash_flow_diagrams/DashFlow.py
dash_flow_diagrams/MiniMap.py
dash_flow_diagrams/__init__.py
dash_flow_diagrams/_imports_.py
dash_flow_diagrams/dash_flow_diagrams.min.js
dash_flow_diagrams/dash_flow_diagrams.min.js.map
dash_flow_diagrams/metadata.json
dash_flow_diagrams/package-info.json
dash_flow_diagrams-0.0.2.dist-info/LICENSE
dash_flow_diagrams-0.0.2.dist-info/METADATA
dash_flow_diagrams-0.0.2.dist-info/WHEEL
dash_flow_diagrams-0.0.2.dist-info/top_level.txt
dash_flow_diagrams-0.0.2.dist-info/RECORD
