Metadata-Version: 2.1
Name: dash-flow-diagrams
Version: 0.0.2
Summary: Project Description
Author: Theodore Tsitsimis <th.tsitsimis@gmail.com>
License: MIT
Classifier: Framework :: Dash
License-File: LICENSE
